ksrdp.cpython-38-x86_64-linux-gnu.so
ksrdp-0.0.2.dist-info/WHEEL
ksrdp-0.0.2.dist-info/METADATA
ksrdp-0.0.2.dist-info/LICENSE
ksrdp-0.0.2.dist-info/RECORD
ksrdp-0.0.2.dist-info/top_level.txt
