Metadata-Version: 2.1
Name: ksrdp
Version: 0.0.2
Summary: Protecting graphs under multiple simultaneous attacks: a heuristic approach
Author-email: Stefan Kapunac <stefankapunac@gmail.com>, Aleksandar Kartelj <aleksandar.kartelj@gmail.com>, Marko Djukanovic <marko.djukanovic@pmf.unibl.org>, Dragan Matic <dragan.matic@pmg.unibl.org>
License: Copyright © 2024 <copyright holders>
Project-URL: Homepage, https://github.com/StefanKapunac/ksrdp
Keywords: Roman domination,VNS
Classifier: License :: OSI Approved :: MIT License
Classifier: Programming Language :: Python :: 3
Classifier: Operating System :: OS Independent
Requires-Python: >=3.8
License-File: LICENSE
Requires-Dist: pybind11
